{
  "alertsData": [
    {
    "id": 111,
    "resident": "Edwin Aldrin",
    "type": "FALL",
    "priority": 2,
    "floor": 1,
    "currentlocation": "Suite 101",
    "icon": "male",
    "description": "Assistance Required",
    "time": 30,
    "media": {
      "video": "https://s3.amazonaws.com/codecademy-content/courses/React/react_video-fast.mp4"
     },
    "location": {
      "room": "Suite 101",
      "xpercent": 5,
      "ypercent": 35
    },
    "history": [
      {
        "priority": 2,
        "timestamp": "04/20/2018 11:30 AM",
        "type": "FALL"
      },
      {
        "priority": 3,
        "timestamp": "04/20/2018 11:40 AM",
        "type": "HIGH IMPACT"
      },
      {
        "priority": 3,
        "timestamp": "04/20/2018 11:43 AM",
        "type": "HIGH IMPACT"
      }
    ]
  },

  {
    "id": 112,
    "resident": "Leon Jenkins",
    "type": "SOS",
    "priority": 1,
    "floor": 1,
    "currentlocation": "Lounge",
    "icon": "male",
    "description": "Help Dispatched",
    "time": 10,
    "media": {
      "video": "https://s3.amazonaws.com/codecademy-content/courses/React/react_video-fast.mp4"
    },
    "location": {
      "room": "Lounge",
      "xpercent": 22,
      "ypercent": 86
    },
    "history": [
      {
        "priority": 2,
        "timestamp": "04/19/2018 11:30 AM",
        "type": "FALL"
      },
      {
        "priority": 1,
        "timestamp": "04/19/2018 12:40 PM",
        "type": "SOS"
      },
      {
        "priority": 3,
        "timestamp": "04/20/2018 11:43 PM",
        "type": "HIGH IMPACT"
      }
    ]
  },

 
  {
    "id": 141,
    "resident": "Holly Mahmood",
    "type": "HIGH IMPACT",
    "priority": 3,
    "floor": 1,
    "currentlocation": "Activity Room",
    "icon": "female",
    "description": "Help Active",
    "time": 5,
    "media": {
      "text": "alert.txt"
    },
    "location": {
      "room": "Suite 102",
      "xpercent": 63,
      "ypercent": 12
    },
    "history": [
      {
        "priority": 4,
        "timestamp": "04/20/2018 11:30 AM",
        "type": "MISSING"
      },
      {
        "priority": 3,
        "timestamp": "04/20/2018 11:40 AM",
        "type": "HIGH IMPACT"
      },
      {
        "priority": 5,
        "timestamp": "04/20/2018 11:43 AM",
        "type": "WAKING UP"
      }
    ]
  },

  {
    "id": 121,
    "resident": "Ali Fulton",
    "type": "FALL",
    "priority": 2,
    "floor": 2,
    "currentlocation": "Suite 201",
    "icon": "female",
    "description": "Help Dispatched",
    "time": 11,
    "media": {
      "audio": "http://www.nihilus.net/soundtracks/Static%20Memories.mp3"
    },
    "location": {
      "room": "Suite 201",
      "xpercent": 15,
      "ypercent": 35
    },
    "history": [
      {
        "priority": 3,
        "timestamp": "04/18/2018 12:30 AM",
        "type": "HIGH IMPACT"
      },
      {
        "priority": 5,
        "timestamp": "04/20/2018 11:40 AM",
        "type": "WAKING UP"
      },
      {
        "priority": 3,
        "timestamp": "04/20/2018 11:43 AM",
        "type": "HIGH IMPACT"
      }
    ]
  },

  {
    "id": 121,
    "resident": "Will Smith",
    "type": "HIGH IMPACT",
    "priority": 3,
    "floor": 1,
    "currentlocation": "Suite 103",
    "icon": "female",
    "description": "Help Dispatched",
    "time": 11,
    "media": {
      "audio": "http://www.nihilus.net/soundtracks/Static%20Memories.mp3"
    },
    "location": {
      "room": "Suite 201",
      "xpercent": 15,
      "ypercent": 35
    },
    "history": [
      {
        "priority": 4,
        "timestamp": "04/18/2018 12:30 AM",
        "type": "MISSING"
      },
      {
        "priority": 5,
        "timestamp": "04/20/2018 11:40 AM",
        "type": "WAKING UP"
      },
      {
        "priority": 3,
        "timestamp": "04/20/2018 11:43 AM",
        "type": "HIGH IMPACT"
      }
    ]
  },

  {
    "id": 101,
    "resident": "David Choi",
    "type": "SOS",
    "priority": 1,
    "floor": 2,
    "currentlocation": "Activity Room",
    "icon": "male",
    "description": "Assistance Required",
    "time": 2,
    "media": {
      "video": "https://s3.amazonaws.com/codecademy-content/courses/React/react_video-fast.mp4"
    },
    "location": {
      "room": "Activity Room",
      "xpercent": 56,
      "ypercent": 74
    },
    "history": [
      {
        "priority": 2,
        "timestamp": "04/19/2018 11:30 AM",
        "type": "FALL"
      },
      {
        "priority": 3,
        "timestamp": "04/20/2018 11:40 AM",
        "type": "HIGH IMPACT"
      },
      {
        "priority": 4,
        "timestamp": "04/20/2018 11:43 AM",
        "type": "MISSING"
      }
    ]
  },

  {
    "id": 119,
    "resident": "Luis R. Carlyle",
    "type": "MISSING",
    "priority": 4,
    "floor": 2,
    "currentlocation": "Suite 202",
    "icon": "male",
    "description": "Assistance Required",
    "time": 30,
    "media": {
      "audio": "http://www.nihilus.net/soundtracks/Static%20Memories.mp3"
    },
    "location": {
      "room": "Suite 202",
      "xpercent": 74,
      "ypercent": 12
    },
    "history": [
      {
        "priority": 1,
        "timestamp": "04/19/2018 10:30 AM",
        "type": "SOS"
      },
      {
        "priority": 2,
        "timestamp": "04/20/2018 11:40 AM",
        "type": "FALL"
      },
      {
        "priority": 5,
        "timestamp": "04/20/2018 11:43 AM",
        "type": "WAKING UP"
      }
    ]
  },

  

  {
    "id": 102,
    "resident": "Sandra Warren",
    "type": "SOS",
    "priority": 1,
    "floor": 2,
    "currentlocation": "Activity Room",
    "icon": "female",
    "description": "Help Active",
    "time": 40,
    "media": {
      "audio": "http://www.nihilus.net/soundtracks/Static%20Memories.mp3"
    },
    "location": {
      "room": "Suite 203",
      "xpercent": 24,
      "ypercent": 84
    },
    "history": [
      {
        "priority": 2,
        "timestamp": "04/20/2018 11:30 AM",
        "type": "FALL"
      },
      {
        "priority": 3,
        "timestamp": "04/20/2018 11:40 AM",
        "type": "HIGH IMPACT"
      },
      {
        "priority": 5,
        "timestamp": "04/20/2018 11:43 AM",
        "type": "WAKING UP"
      }
    ]
  },

  

  {
    "id": 221,
    "resident": "Thomas A. Gaines",
    "type": "MISSING",
    "priority": 4,
    "floor": 3,
    "currentlocation": "Unknown",
    "icon": "male",
    "description": "Help Active",
    "time": 30,
    "media": {
      "text": "alert.txt"
    },
    "location": {
      "room": "Suite 301",
      "xpercent": 15,
      "ypercent": 21
    },
    "history": [
      {
        "priority": 2,
        "timestamp": "04/19/2018 5:55 PM",
        "type": "FALL"
      },
      {
        "priority": 2,
        "timestamp": "04/20/2018 8:40 AM",
        "type": "FALL"
      },
      {
        "priority": 5,
        "timestamp": "04/20/2018 11:43 AM",
        "type": "WAKING UP"
      }
    ]
  },

  {
    "id": 197,
    "resident": "Jennifer Carpenter",
    "type": "WAKING UP",
    "priority": 5,
    "floor": 3,
    "currentlocation": "Lounge",
    "icon": "female",
    "description": "Assistance Required",
    "time": 3,
    "media": {
      "audio": "http://www.nihilus.net/soundtracks/Static%20Memories.mp3"
    },
    "location": {
      "room": "Lounge",
      "xpercent": 67,
      "ypercent": 43
    },
    "history": [
      {
        "priority": 2,
        "timestamp": "04/17/2018 10:21 AM",
        "type": "FALL"
      },
      {
        "priority": 3,
        "timestamp": "04/19/2018 11:11 AM",
        "type": "HIGH IMPACT"
      },
      {
        "priority": 1,
        "timestamp": "04/20/2018 9:13 AM",
        "type": "SOS"
      }
    ]
  },

  {
    "id": 197,
    "resident": "Saoirse Ronan",
    "type": "MISSING",
    "priority": 4,
    "floor": 3,
    "currentlocation": "Lounge",
    "icon": "female",
    "description": "Assistance Required",
    "time": 3,
    "media": {
      "audio": "http://www.nihilus.net/soundtracks/Static%20Memories.mp3"
    },
    "location": {
      "room": "Lounge",
      "xpercent": 57,
      "ypercent": 33
    },
    "history": [
      {
        "priority": 2,
        "timestamp": "04/17/2018 10:21 AM",
        "type": "FALL"
      },
      {
        "priority": 5,
        "timestamp": "04/19/2018 11:11 AM",
        "type": "WAKING UP"
      },
      {
        "priority": 1,
        "timestamp": "04/20/2018 9:13 AM",
        "type": "SOS"
      }
    ]
  },

  {
    "id": 203,
    "resident": "Lily Denton",
    "type": "SOS",
    "priority": 1,
    "floor": 3,
    "currentlocation": "Suite 302",
    "icon": "female",
    "description": "Assistance Required",
    "time": 21,
    "media": {
      "text": "alert.txt"
    },
    "location": {
      "room": "Suite 302",
      "xpercent": 94,
      "ypercent": 65
    },
    "history": [
      {
        "priority": 2,
        "timestamp": "04/18/2018 8:27 AM",
        "type": "FALL"
      },
      {
        "priority": 4,
        "timestamp": "04/19/2018 11:40 PM",
        "type": "MISSING"
      },
      {
        "priority": 2,
        "timestamp": "04/20/2018 10:03 AM",
        "type": "FALL"
      }
    ]
  }
  ],
  
  "futureAlertsData": [
    {
    "id": 111,
    "resident": "Edwin Aldrin",
    "type": "FALL",
    "priority": 2,
    "floor": 1,
    "currentlocation": "Suite 101",
    "icon": "male",
    "description": "Help Dispatched",
    "time": 10,
    "media": {
      "video": "https://s3.amazonaws.com/codecademy-content/courses/React/react_video-fast.mp4"
     },
    "location": {
      "room": "Suite 101",
      "xpercent": 5,
      "ypercent": 35
    },
    "history": [
      {
        "priority": 2,
        "timestamp": "04/20/2018 11:30 AM",
        "type": "FALL"
      },
      {
        "priority": 3,
        "timestamp": "04/20/2018 11:40 AM",
        "type": "HIGH IMPACT"
      },
      {
        "priority": 3,
        "timestamp": "04/20/2018 11:43 AM",
        "type": "HIGH IMPACT"
      }
    ]
  },

  {
    "id": 112,
    "resident": "Leon Jenkins",
    "type": "SOS",
    "priority": 1,
    "floor": 1,
    "currentlocation": "Lounge",
    "icon": "male",
    "description": "Help Active",
    "time": 20,
    "media": {
      "video": "https://s3.amazonaws.com/codecademy-content/courses/React/react_video-fast.mp4"
    },
    "location": {
      "room": "Lounge",
      "xpercent": 22,
      "ypercent": 86
    },
    "history": [
      {
        "priority": 2,
        "timestamp": "04/19/2018 11:30 AM",
        "type": "FALL"
      },
      {
        "priority": 1,
        "timestamp": "04/19/2018 12:40 PM",
        "type": "SOS"
      },
      {
        "priority": 3,
        "timestamp": "04/20/2018 11:43 PM",
        "type": "HIGH IMPACT"
      }
    ]
  },


  {
    "id": 121,
    "resident": "Ali Fulton",
    "type": "FALL",
    "priority": 2,
    "floor": 2,
    "currentlocation": "Suite 201",
    "icon": "female",
    "description": "Help Active",
    "time": 21,
    "media": {
      "audio": "http://www.nihilus.net/soundtracks/Static%20Memories.mp3"
    },
    "location": {
      "room": "Suite 201",
      "xpercent": 15,
      "ypercent": 35
    },
    "history": [
      {
        "priority": 3,
        "timestamp": "04/18/2018 12:30 AM",
        "type": "HIGH IMPACT"
      },
      {
        "priority": 5,
        "timestamp": "04/20/2018 11:40 AM",
        "type": "WAKING UP"
      },
      {
        "priority": 3,
        "timestamp": "04/20/2018 11:43 AM",
        "type": "HIGH IMPACT"
      }
    ]
  },

  {
    "id": 121,
    "resident": "Will Smith",
    "type": "HIGH IMPACT",
    "priority": 3,
    "floor": 1,
    "currentlocation": "Suite 103",
    "icon": "female",
    "description": "Help Active",
    "time": 21,
    "media": {
      "audio": "http://www.nihilus.net/soundtracks/Static%20Memories.mp3"
    },
    "location": {
      "room": "Suite 201",
      "xpercent": 15,
      "ypercent": 35
    },
    "history": [
      {
        "priority": 4,
        "timestamp": "04/18/2018 12:30 AM",
        "type": "MISSING"
      },
      {
        "priority": 5,
        "timestamp": "04/20/2018 11:40 AM",
        "type": "WAKING UP"
      },
      {
        "priority": 3,
        "timestamp": "04/20/2018 11:43 AM",
        "type": "HIGH IMPACT"
      }
    ]
  },

  {
    "id": 101,
    "resident": "David Choi",
    "type": "SOS",
    "priority": 1,
    "floor": 2,
    "currentlocation": "Activity Room",
    "icon": "male",
    "description": "Help Active",
    "time": 22,
    "media": {
      "video": "https://s3.amazonaws.com/codecademy-content/courses/React/react_video-fast.mp4"
    },
    "location": {
      "room": "Activity Room",
      "xpercent": 56,
      "ypercent": 74
    },
    "history": [
      {
        "priority": 2,
        "timestamp": "04/19/2018 11:30 AM",
        "type": "FALL"
      },
      {
        "priority": 3,
        "timestamp": "04/20/2018 11:40 AM",
        "type": "HIGH IMPACT"
      },
      {
        "priority": 4,
        "timestamp": "04/20/2018 11:43 AM",
        "type": "MISSING"
      }
    ]
  },

  {
    "id": 119,
    "resident": "Luis R. Carlyle",
    "type": "MISSING",
    "priority": 4,
    "floor": 2,
    "currentlocation": "Suite 202",
    "icon": "male",
    "description": "Help Dispatched",
    "time": 40,
    "media": {
      "audio": "http://www.nihilus.net/soundtracks/Static%20Memories.mp3"
    },
    "location": {
      "room": "Suite 202",
      "xpercent": 74,
      "ypercent": 12
    },
    "history": [
      {
        "priority": 1,
        "timestamp": "04/19/2018 10:30 AM",
        "type": "SOS"
      },
      {
        "priority": 2,
        "timestamp": "04/20/2018 11:40 AM",
        "type": "FALL"
      },
      {
        "priority": 5,
        "timestamp": "04/20/2018 11:43 AM",
        "type": "WAKING UP"
      }
    ]
  },

  {
    "id": 197,
    "resident": "Jennifer Carpenter",
    "type": "WAKING UP",
    "priority": 5,
    "floor": 3,
    "currentlocation": "Lounge",
    "icon": "female",
    "description": "Help Dispatched",
    "time": 13,
    "media": {
      "audio": "http://www.nihilus.net/soundtracks/Static%20Memories.mp3"
    },
    "location": {
      "room": "Lounge",
      "xpercent": 67,
      "ypercent": 43
    },
    "history": [
      {
        "priority": 2,
        "timestamp": "04/17/2018 10:21 AM",
        "type": "FALL"
      },
      {
        "priority": 3,
        "timestamp": "04/19/2018 11:11 AM",
        "type": "HIGH IMPACT"
      },
      {
        "priority": 1,
        "timestamp": "04/20/2018 9:13 AM",
        "type": "SOS"
      }
    ]
  },

  {
    "id": 197,
    "resident": "Saoirse Ronan",
    "type": "MISSING",
    "priority": 4,
    "floor": 3,
    "currentlocation": "Lounge",
    "icon": "female",
    "description": "Help Dispatched",
    "time": 13,
    "media": {
      "audio": "http://www.nihilus.net/soundtracks/Static%20Memories.mp3"
    },
    "location": {
      "room": "Lounge",
      "xpercent": 57,
      "ypercent": 33
    },
    "history": [
      {
        "priority": 2,
        "timestamp": "04/17/2018 10:21 AM",
        "type": "FALL"
      },
      {
        "priority": 5,
        "timestamp": "04/19/2018 11:11 AM",
        "type": "WAKING UP"
      },
      {
        "priority": 1,
        "timestamp": "04/20/2018 9:13 AM",
        "type": "SOS"
      }
    ]
  },

  {
    "id": 203,
    "resident": "Lily Denton",
    "type": "SOS",
    "priority": 1,
    "floor": 3,
    "currentlocation": "Suite 302",
    "icon": "female",
    "description": "Help Dispatched",
    "time": 31,
    "media": {
      "text": "alert.txt"
    },
    "location": {
      "room": "Suite 302",
      "xpercent": 94,
      "ypercent": 65
    },
    "history": [
      {
        "priority": 2,
        "timestamp": "04/18/2018 8:27 AM",
        "type": "FALL"
      },
      {
        "priority": 4,
        "timestamp": "04/19/2018 11:40 PM",
        "type": "MISSING"
      },
      {
        "priority": 2,
        "timestamp": "04/20/2018 10:03 AM",
        "type": "FALL"
      }
    ]
  },

  {
    "id": 303,
    "resident": "Ted Moseby",
    "type": "SOS",
    "priority": 1,
    "floor": 3,
    "currentlocation": "Activity Room",
    "icon": "male",
    "description": "Assistance Required",
    "time": 5,
    "media": {
      "text": "alert.txt"
    },
    "location": {
      "room": "Suite 302",
      "xpercent": 94,
      "ypercent": 65
    },
    "history": [
      {
        "priority": 1,
        "timestamp": "04/18/2018 8:27 AM",
        "type": "SOS"
      },
      {
        "priority": 4,
        "timestamp": "04/19/2018 11:40 PM",
        "type": "MISSING"
      },
      {
        "priority": 3,
        "timestamp": "04/20/2018 10:03 AM",
        "type": "HIGH IMPACT"
      }
    ]
  },

  {
    "id": 310,
    "resident": "Rachel Green",
    "type": "HIGH IMPACT",
    "priority": 3,
    "floor": 1,
    "currentlocation": "Suite 102",
    "icon": "female",
    "description": "Assistance Required",
    "time": 1,
    "media": {
      "text": "alert.txt"
    },
    "location": {
      "room": "Suite 302",
      "xpercent": 34,
      "ypercent": 42
    },
    "history": [
      {
        "priority": 2,
        "timestamp": "04/18/2018 8:27 AM",
        "type": "FALL"
      },
      {
        "priority": 4,
        "timestamp": "04/19/2018 11:40 PM",
        "type": "MISSING"
      },
      {
        "priority": 2,
        "timestamp": "04/20/2018 10:03 AM",
        "type": "FALL"
      }
    ]
  }

  ],

  "futureAlertsData2": [
    {
    "id": 111,
    "resident": "Edwin Aldrin",
    "type": "FALL",
    "priority": 2,
    "floor": 1,
    "currentlocation": "Suite 101",
    "icon": "male",
    "description": "Help Active",
    "time": 20,
    "media": {
      "video": "https://s3.amazonaws.com/codecademy-content/courses/React/react_video-fast.mp4"
     },
    "location": {
      "room": "Suite 101",
      "xpercent": 5,
      "ypercent": 35
    },
    "history": [
      {
        "priority": 2,
        "timestamp": "04/20/2018 11:30 AM",
        "type": "FALL"
      },
      {
        "priority": 3,
        "timestamp": "04/20/2018 11:40 AM",
        "type": "HIGH IMPACT"
      },
      {
        "priority": 3,
        "timestamp": "04/20/2018 11:43 AM",
        "type": "HIGH IMPACT"
      }
    ]
  },


  {
    "id": 119,
    "resident": "Luis R. Carlyle",
    "type": "MISSING",
    "priority": 4,
    "floor": 2,
    "currentlocation": "Suite 202",
    "icon": "male",
    "description": "Help Active",
    "time": 50,
    "media": {
      "audio": "http://www.nihilus.net/soundtracks/Static%20Memories.mp3"
    },
    "location": {
      "room": "Suite 202",
      "xpercent": 74,
      "ypercent": 12
    },
    "history": [
      {
        "priority": 1,
        "timestamp": "04/19/2018 10:30 AM",
        "type": "SOS"
      },
      {
        "priority": 2,
        "timestamp": "04/20/2018 11:40 AM",
        "type": "FALL"
      },
      {
        "priority": 5,
        "timestamp": "04/20/2018 11:43 AM",
        "type": "WAKING UP"
      }
    ]
  },

  {
    "id": 197,
    "resident": "Jennifer Carpenter",
    "type": "WAKING UP",
    "priority": 5,
    "floor": 3,
    "currentlocation": "Lounge",
    "icon": "female",
    "description": "Help Active",
    "time": 23,
    "media": {
      "audio": "http://www.nihilus.net/soundtracks/Static%20Memories.mp3"
    },
    "location": {
      "room": "Lounge",
      "xpercent": 67,
      "ypercent": 43
    },
    "history": [
      {
        "priority": 2,
        "timestamp": "04/17/2018 10:21 AM",
        "type": "FALL"
      },
      {
        "priority": 3,
        "timestamp": "04/19/2018 11:11 AM",
        "type": "HIGH IMPACT"
      },
      {
        "priority": 1,
        "timestamp": "04/20/2018 9:13 AM",
        "type": "SOS"
      }
    ]
  },

  {
    "id": 197,
    "resident": "Saoirse Ronan",
    "type": "MISSING",
    "priority": 4,
    "floor": 3,
    "currentlocation": "Lounge",
    "icon": "female",
    "description": "Help Active",
    "time": 23,
    "media": {
      "audio": "http://www.nihilus.net/soundtracks/Static%20Memories.mp3"
    },
    "location": {
      "room": "Lounge",
      "xpercent": 57,
      "ypercent": 33
    },
    "history": [
      {
        "priority": 2,
        "timestamp": "04/17/2018 10:21 AM",
        "type": "FALL"
      },
      {
        "priority": 5,
        "timestamp": "04/19/2018 11:11 AM",
        "type": "WAKING UP"
      },
      {
        "priority": 1,
        "timestamp": "04/20/2018 9:13 AM",
        "type": "SOS"
      }
    ]
  },

  {
    "id": 203,
    "resident": "Lily Denton",
    "type": "SOS",
    "priority": 1,
    "floor": 3,
    "currentlocation": "Suite 302",
    "icon": "female",
    "description": "Help Active",
    "time": 41,
    "media": {
      "text": "alert.txt"
    },
    "location": {
      "room": "Suite 302",
      "xpercent": 94,
      "ypercent": 65
    },
    "history": [
      {
        "priority": 2,
        "timestamp": "04/18/2018 8:27 AM",
        "type": "FALL"
      },
      {
        "priority": 4,
        "timestamp": "04/19/2018 11:40 PM",
        "type": "MISSING"
      },
      {
        "priority": 2,
        "timestamp": "04/20/2018 10:03 AM",
        "type": "FALL"
      }
    ]
  },

  {
    "id": 303,
    "resident": "Ted Moseby",
    "type": "SOS",
    "priority": 1,
    "floor": 3,
    "currentlocation": "Activity Room",
    "icon": "male",
    "description": "Help Dispatched",
    "time": 15,
    "media": {
      "text": "alert.txt"
    },
    "location": {
      "room": "Suite 302",
      "xpercent": 94,
      "ypercent": 65
    },
    "history": [
      {
        "priority": 1,
        "timestamp": "04/18/2018 8:27 AM",
        "type": "SOS"
      },
      {
        "priority": 4,
        "timestamp": "04/19/2018 11:40 PM",
        "type": "MISSING"
      },
      {
        "priority": 3,
        "timestamp": "04/20/2018 10:03 AM",
        "type": "HIGH IMPACT"
      }
    ]
  },

  {
    "id": 310,
    "resident": "Rachel Green",
    "type": "HIGH IMPACT",
    "priority": 3,
    "floor": 1,
    "currentlocation": "Suite 102",
    "icon": "female",
    "description": "Help Dispatched",
    "time": 11,
    "media": {
      "text": "alert.txt"
    },
    "location": {
      "room": "Suite 302",
      "xpercent": 34,
      "ypercent": 42
    },
    "history": [
      {
        "priority": 2,
        "timestamp": "04/18/2018 8:27 AM",
        "type": "FALL"
      },
      {
        "priority": 4,
        "timestamp": "04/19/2018 11:40 PM",
        "type": "MISSING"
      },
      {
        "priority": 2,
        "timestamp": "04/20/2018 10:03 AM",
        "type": "FALL"
      }
    ]
  },

  {
    "id": 316,
    "resident": "Wesley Chan",
    "type": "MISSING",
    "priority": 4,
    "floor": 2,
    "currentlocation": "Suite 202",
    "icon": "male",
    "description": "Assistance Required",
    "time": 1,
    "media": {
      "text": "alert.txt"
    },
    "location": {
      "room": "Suite 302",
      "xpercent": 44,
      "ypercent": 22
    },
    "history": [
      {
        "priority": 2,
        "timestamp": "04/18/2018 8:27 AM",
        "type": "FALL"
      },
      {
        "priority": 4,
        "timestamp": "04/19/2018 11:40 PM",
        "type": "MISSING"
      },
      {
        "priority": 2,
        "timestamp": "04/20/2018 10:03 AM",
        "type": "FALL"
      }
    ]
  }

  ],

  "userData": {
    "name": "Kim Sears",
    "id": "145265",
    "password": "kim@1234",
    "facility": "Ashby Ponds",
    "role": "Nurse",
    "defaultfloor": 2,
    "lastlogin": "04/20/2018 11:43 AM"
  },

  "floorsData": {
    "defaultfloor": 2,
    "details": [
      {
        "facility": "Ashby Ponds",
        "floor": 1,
        "floormap": "media1@url"
      },
      {
        "facility": "Ashby Ponds",
        "floor": 2,
        "floormap": "media2@url"
      },
      {
        "facility": "Ashby Ponds",
        "floor": 3,
        "floormap": "media3@url"
      }
    ]
  },
  
  "patientsData": [
    {
    "id": 1,
    "name": "Leanne Graham",
    "emergency": "Bret Graham",
    "email": "Sincere@april.biz",
    "address": {
      "street": "Kulas Light",
      "suite": "Apt. 556",
      "city": "Gwenborough",
      "zipcode": "92998-3874"
    },
    "phone": "1-770-736-8031 x56442",
    "consulting": {
      "name": "Dr. Romaguera Crona",
      "phone": "225-555-0182",
      "speciality": "Rheumatologist"
    }
  },
  {
    "id": 2,
    "name": "Ervin Howell",
    "emergency": "Antonette Howell",
    "email": "Shanna@melissa.tv",
    "address": {
      "street": "Victor Plains",
      "suite": "Suite 879",
      "city": "Wisokyburgh",
      "zipcode": "90566-7771"
    },
    "phone": "010-692-6593 x09125",
    "consulting": {
      "name": "Dr. Deckow Crist",
      "phone": "225-555-0178",
      "speciality": "Endocrinologist"
    }
  },
  {
    "id": 3,
    "name": "Clementine Bauch",
    "emergency": "Samantha Albright",
    "email": "Nathan@yesenia.net",
    "address": {
      "street": "Douglas Extension",
      "suite": "Suite 847",
      "city": "McKenziehaven",
      "zipcode": "59590-4157"
    },
    "phone": "1-463-123-4447",
    "consulting": {
      "name": "Dr. Romaguera Jacobson",
      "phone": "225-555-0195",
      "speciality": "Cardiologist"
    }
  },
  {
    "id": 4,
    "name": "Patrick Lebsack",
    "emergency": "Karianne Benoist",
    "email": "Julianne.OConner@kory.org",
    "address": {
      "street": "Hoeger Mall",
      "suite": "Apt. 692",
      "city": "South Elvis",
      "zipcode": "53919-4257"
    },
    "phone": "493-170-9623 x156",
    "consulting": {
      "name": "Dr. Robel Corkery",
      "phone": "225-555-0183",
      "speciality": "Gynaecologist"
    }
  },
  {
    "id": 5,
    "name": "Chelsey Dietrich",
    "emergency": "Kamren Gomez",
    "email": "Lucio_Hettinger@annie.ca",
    "address": {
      "street": "Skiles Walks",
      "suite": "Suite 351",
      "city": "Roscoeview",
      "zipcode": "33263"
    },
    "phone": "(254)954-1289",
    "consulting": {
      "name": "Dr. Stacy Keebler",
      "phone": "202-555-0109",
      "speciality": "Gynaecologist"
    }
  },
  {
    "id": 6,
    "name": "Mrs. Dennis Schulist",
    "emergency": "Leopold Corkery",
    "email": "Karley_Dach@jasper.info",
    "address": {
      "street": "Norberto Crossing",
      "suite": "Apt. 950",
      "city": "South Christy",
      "zipcode": "23505-1337"
    },
    "phone": "1-477-935-8478 x6430",
    "consulting": {
      "name": "Dr. Considine Lockman",
      "phone": "202-555-0134",
      "speciality": "Oncologist"
    }
  },
  {
    "id": 7,
    "name": "Kurtis Weissnat",
    "emergency": "Elwyn Skiles",
    "email": "Telly.Hoeger@billy.biz",
    "address": {
      "street": "Rex Trail",
      "suite": "Suite 280",
      "city": "Howemouth",
      "zipcode": "58804-1099"
    },
    "phone": "210.067.6132",
    "consulting": {
      "name": "Dr. Albert Johnson",
      "phone": "202-555-0121",
      "speciality": "Oncologist"
    }
  },
  {
    "id": 8,
    "name": "Nicholas Gaines V",
    "emergency": "Maxime Nienow",
    "email": "Sherwood@rosamond.me",
    "address": {
      "street": "Ellsworth Summit",
      "suite": "Suite 729",
      "city": "Aliyaview",
      "zipcode": "45169"
    },
    "phone": "586.493.6943 x140",
    "consulting": {
      "name": "Dr. Nicholas Abernathy",
      "phone": "202-555-0189",
      "speciality": "Cardiologist"
    }
  },
  {
    "id": 9,
    "name": "Glenna Reichert",
    "emergency": "Delphine Reichert",
    "email": "Chaim_McDermott@dana.io",
    "address": {
      "street": "Dayna Park",
      "suite": "Suite 449",
      "city": "Bartholomebury",
      "zipcode": "76495-3109"
    },
    "phone": "(775)976-6794 x41206",
    "consulting": {
      "name": "Dr. Rajeev Shivkumar",
      "phone": "202-555-0178",
      "speciality": "Endocrinologist"
    }
  },
  {
    "id": 10,
    "name": "Clementina DuBuque",
    "emergency": "Moriah Stanton",
    "email": "Rey.Padberg@karina.biz",
    "address": {
      "street": "Kattie Turnpike",
      "suite": "Suite 198",
      "city": "Lebsackbury",
      "zipcode": "31428-2261"
    },
    "phone": "024-648-3804",
    "consulting": {
      "name": "Dr. Roger Goodell",
      "phone": "202-555-0116",
      "speciality": "Rheumatologist"
    }
  }
  ],

  "login": { "status": "accepted" }
}